Workbook
Name Cfg_BaselineDate: Config!$B$2
Name Cfg_BaselineOpeningValue: Config!$B$3
Name Cfg_CovWarn: Config!$B$5
Name Cfg_HiMove: Config!$B$4
Name Cfg_Today: Config!$B$1
Name Mov_COGSValue: Movements!$H$2:$H$2052
Name Mov_Date: Movements!$A$2:$A$2052
Name Mov_Item: Movements!$B$2:$B$2052
Name Mov_Qty: Movements!$C$2:$C$2052
Name Mov_Type: Movements!$D$2:$D$2052
Name Mov_Value: Movements!$G$2:$G$2052
Name Sales_Amount: Sales!$E$2:$E$2018
Name Sales_Date: Sales!$A$2:$A$2018

Sheet Items
A1: ItemID | B1: ItemName | C1: Category | D1: Unit | E1: Cost_No_Tax | F1: MinStock | G1: MOQ | H1: LeadTimeDays | I1: SafetyStock | J1: OnHand | K1: StockValue | L1: ThisMonthCons | M1: LastMonthCons | N1: TwoMonthsAgoCons | O1: Avg3MCons | P1: HighMover | Q1: ReorderPoint | R1: NeedToOrder | S1: SuggestedOrderQty | T1: CoverageDays | V1: StartOfThisMonth | W1: EndOfThisMonth | X1: StartOfLastMonth | Y1: EndOfLastMonth | Z1: StartOfTwoAgo | AA1: EndOfTwoAgo
A2: ITM-001 | B2: Lithium Cell 21700 | C2: Cells | D2: pcs | E2: 210 | F2: 500 | G2: 200 | H2: 20 | I2: 300 | J2: =IF($A2="","", SUMIFS(Mov_Qty, Mov_Item, $A2)) -> 0 | K2: =IF($A2="","", J2 * $E2) -> 0 | L2: =IF($A2="","", SUMIFS(-Mov_Qty, Mov_Item, $A2, Mov_Type, "Consumption", Mov_Date, ">="&$V$2, Mov_Date, "<="&$W$2)) -> 0 | M2: =IF($A2="","", SUMIFS(-Mov_Qty, Mov_Item, $A2, Mov_Type, "Consumption", Mov_Date, ">="&$X$2, Mov_Date, "<="&$Y$2)) -> 0 | N2: =IF($A2="","", SUMIFS(-Mov_Qty, Mov_Item, $A2, Mov_Type, "Consumption", Mov_Date, ">="&$Z$2, Mov_Date, "<="&$AA$2)) -> 0 | O2: =IFERROR(AVERAGE(L2:N2),"") -> 0 | P2: =IF(O2>=Cfg_HiMove, "Yes", "") -> 0 | Q2: =IF($A2="","", $I2 + IFERROR(O2/30*$H2,0)) -> 0 | R2: =IF($A2="","", IF(J2<=$F2, "Yes", "")) -> 0 | S2: =IF(R2="Yes", CEILING(MAX($G2, Q2-J2), $G2), 0) -> 0 | T2: =IFERROR(J2/(O2/30),"") -> 0 | V2: =EOMONTH(Cfg_Today,-1)+1 -> 0 | W2: =EOMONTH(Cfg_Today,0) -> 0 | X2: =EOMONTH(Cfg_Today,-2)+1 -> 0 | Y2: =EOMONTH(Cfg_Today,-1) -> 0 | Z2: =EOMONTH(Cfg_Today,-3)+1 -> 0 | AA2: =EOMONTH(Cfg_Today,-2) -> 0
A3: ITM-002 | B3: BMS 16S 60A | C3: BMS | D3: pcs | E3: 950 | F3: 50 | G3: 10 | H3: 15 | I3: 30 | J3: =IF($A3="","", SUMIFS(Mov_Qty, Mov_Item, $A3)) -> 0 | K3: =IF($A3="","", J3 * $E3) -> 0 | L3: =IF($A3="","", SUMIFS(-Mov_Qty, Mov_Item, $A3, Mov_Type, "Consumption", Mov_Date, ">="&$V$2, Mov_Date, "<="&$W$2)) -> 0 | M3: =IF($A3="","", SUMIFS(-Mov_Qty, Mov_Item, $A3, Mov_Type, "Consumption", Mov_Date, ">="&$X$2, Mov_Date, "<="&$Y$2)) -> 0 | N3: =IF($A3="","", SUMIFS(-Mov_Qty, Mov_Item, $A3, Mov_Type, "Consumption", Mov_Date, ">="&$Z$2, Mov_Date, "<="&$AA$2)) -> 0 | O3: =IFERROR(AVERAGE(L3:N3),"") -> 0 | P3: =IF(O3>=Cfg_HiMove, "Yes", "") -> 0 | Q3: =IF($A3="","", $I3 + IFERROR(O3/30*$H3,0)) -> 0 | R3: =IF($A3="","", IF(J3<=$F3, "Yes", "")) -> 0 | S3: =IF(R3="Yes", CEILING(MAX($G3, Q3-J3), $G3), 0) -> 0 | T3: =IFERROR(J3/(O3/30),"") -> 0
A4: ITM-003 | B4: Charger 60V 10A | C4: Charger | D4: pcs | E4: 1800 | F4: 20 | G4: 5 | H4: 10 | I4: 10 | J4: =IF($A4="","", SUMIFS(Mov_Qty, Mov_Item, $A4)) -> 0 | K4: =IF($A4="","", J4 * $E4) -> 0 | L4: =IF($A4="","", SUMIFS(-Mov_Qty, Mov_Item, $A4, Mov_Type, "Consumption", Mov_Date, ">="&$V$2, Mov_Date, "<="&$W$2)) -> 0 | M4: =IF($A4="","", SUMIFS(-Mov_Qty, Mov_Item, $A4, Mov_Type, "Consumption", Mov_Date, ">="&$X$2, Mov_Date, "<="&$Y$2)) -> 0 | N4: =IF($A4="","", SUMIFS(-Mov_Qty, Mov_Item, $A4, Mov_Type, "Consumption", Mov_Date, ">="&$Z$2, Mov_Date, "<="&$AA$2)) -> 0 | O4: =IFERROR(AVERAGE(L4:N4),"") -> 0 | P4: =IF(O4>=Cfg_HiMove, "Yes", "") -> 0 | Q4: =IF($A4="","", $I4 + IFERROR(O4/30*$H4,0)) -> 0 | R4: =IF($A4="","", IF(J4<=$F4, "Yes", "")) -> 0 | S4: =IF(R4="Yes", CEILING(MAX($G4, Q4-J4), $G4), 0) -> 0 | T4: =IFERROR(J4/(O4/30),"") -> 0
A5: ITM-004 | B5: PVC Sleeve 21700 | C5: Consumable | D5: m | E5: 4.5 | F5: 1000 | G5: 2000 | H5: 7 | I5: 500 | J5: =IF($A5="","", SUMIFS(Mov_Qty, Mov_Item, $A5)) -> 0 | K5: =IF($A5="","", J5 * $E5) -> 0 | L5: =IF($A5="","", SUMIFS(-Mov_Qty, Mov_Item, $A5, Mov_Type, "Consumption", Mov_Date, ">="&$V$2, Mov_Date, "<="&$W$2)) -> 0 | M5: =IF($A5="","", SUMIFS(-Mov_Qty, Mov_Item, $A5, Mov_Type, "Consumption", Mov_Date, ">="&$X$2, Mov_Date, "<="&$Y$2)) -> 0 | N5: =IF($A5="","", SUMIFS(-Mov_Qty, Mov_Item, $A5, Mov_Type, "Consumption", Mov_Date, ">="&$Z$2, Mov_Date, "<="&$AA$2)) -> 0 | O5: =IFERROR(AVERAGE(L5:N5),"") -> 0 | P5: =IF(O5>=Cfg_HiMove, "Yes", "") -> 0 | Q5: =IF($A5="","", $I5 + IFERROR(O5/30*$H5,0)) -> 0 | R5: =IF($A5="","", IF(J5<=$F5, "Yes", "")) -> 0 | S5: =IF(R5="Yes", CEILING(MAX($G5, Q5-J5), $G5), 0) -> 0 | T5: =IFERROR(J5/(O5/30),"") -> 0
J6: =IF($A6="","", SUMIFS(Mov_Qty, Mov_Item, $A6)) -> 0 | K6: =IF($A6="","", J6 * $E6) -> 0 | L6: =IF($A6="","", SUMIFS(-Mov_Qty, Mov_Item, $A6, Mov_Type, "Consumption", Mov_Date, ">="&$V$2, Mov_Date, "<="&$W$2)) -> 0 | M6: =IF($A6="","", SUMIFS(-Mov_Qty, Mov_Item, $A6, Mov_Type, "Consumption", Mov_Date, ">="&$X$2, Mov_Date, "<="&$Y$2)) -> 0 | N6: =IF($A6="","", SUMIFS(-Mov_Qty, Mov_Item, $A6, Mov_Type, "Consumption", Mov_Date, ">="&$Z$2, Mov_Date, "<="&$AA$2)) -> 0 | O6: =IFERROR(AVERAGE(L6:N6),"") -> 0 | P6: =IF(O6>=Cfg_HiMove, "Yes", "") -> 0 | Q6: =IF($A6="","", $I6 + IFERROR(O6/30*$H6,0)) -> 0 | R6: =IF($A6="","", IF(J6<=$F6, "Yes", "")) -> 0 | S6: =IF(R6="Yes", CEILING(MAX($G6, Q6-J6), $G6), 0) -> 0 | T6: =IFERROR(J6/(O6/30),"") -> 0
J7: =IF($A7="","", SUMIFS(Mov_Qty, Mov_Item, $A7)) -> 0 | K7: =IF($A7="","", J7 * $E7) -> 0 | L7: =IF($A7="","", SUMIFS(-Mov_Qty, Mov_Item, $A7, Mov_Type, "Consumption", Mov_Date, ">="&$V$2, Mov_Date, "<="&$W$2)) -> 0 | M7: =IF($A7="","", SUMIFS(-Mov_Qty, Mov_Item, $A7, Mov_Type, "Consumption", Mov_Date, ">="&$X$2, Mov_Date, "<="&$Y$2)) -> 0 | N7: =IF($A7="","", SUMIFS(-Mov_Qty, Mov_Item, $A7, Mov_Type, "Consumption", Mov_Date, ">="&$Z$2, Mov_Date, "<="&$AA$2)) -> 0 | O7: =IFERROR(AVERAGE(L7:N7),"") -> 0 | P7: =IF(O7>=Cfg_HiMove, "Yes", "") -> 0 | Q7: =IF($A7="","", $I7 + IFERROR(O7/30*$H7,0)) -> 0 | R7: =IF($A7="","", IF(J7<=$F7, "Yes", "")) -> 0 | S7: =IF(R7="Yes", CEILING(MAX($G7, Q7-J7), $G7), 0) -> 0 | T7: =IFERROR(J7/(O7/30),"") -> 0
J8: =IF($A8="","", SUMIFS(Mov_Qty, Mov_Item, $A8)) -> 0 | K8: =IF($A8="","", J8 * $E8) -> 0 | L8: =IF($A8="","", SUMIFS(-Mov_Qty, Mov_Item, $A8, Mov_Type, "Consumption", Mov_Date, ">="&$V$2, Mov_Date, "<="&$W$2)) -> 0 | M8: =IF($A8="","", SUMIFS(-Mov_Qty, Mov_Item, $A8, Mov_Type, "Consumption", Mov_Date, ">="&$X$2, Mov_Date, "<="&$Y$2)) -> 0 | N8: =IF($A8="","", SUMIFS(-Mov_Qty, Mov_Item, $A8, Mov_Type, "Consumption", Mov_Date, ">="&$Z$2, Mov_Date, "<="&$AA$2)) -> 0 | O8: =IFERROR(AVERAGE(L8:N8),"") -> 0 | P8: =IF(O8>=Cfg_HiMove, "Yes", "") -> 0 | Q8: =IF($A8="","", $I8 + IFERROR(O8/30*$H8,0)) -> 0 | R8: =IF($A8="","", IF(J8<=$F8, "Yes", "")) -> 0 | S8: =IF(R8="Yes", CEILING(MAX($G8, Q8-J8), $G8), 0) -> 0 | T8: =IFERROR(J8/(O8/30),"") -> 0
J9: =IF($A9="","", SUMIFS(Mov_Qty, Mov_Item, $A9)) -> 0 | K9: =IF($A9="","", J9 * $E9) -> 0 | L9: =IF($A9="","", SUMIFS(-Mov_Qty, Mov_Item, $A9, Mov_Type, "Consumption", Mov_Date, ">="&$V$2, Mov_Date, "<="&$W$2)) -> 0 | M9: =IF($A9="","", SUMIFS(-Mov_Qty, Mov_Item, $A9, Mov_Type, "Consumption", Mov_Date, ">="&$X$2, Mov_Date, "<="&$Y$2)) -> 0 | N9: =IF($A9="","", SUMIFS(-Mov_Qty, Mov_Item, $A9, Mov_Type, "Consumption", Mov_Date, ">="&$Z$2, Mov_Date, "<="&$AA$2)) -> 0 | O9: =IFERROR(AVERAGE(L9:N9),"") -> 0 | P9: =IF(O9>=Cfg_HiMove, "Yes", "") -> 0 | Q9: =IF($A9="","", $I9 + IFERROR(O9/30*$H9,0)) -> 0 | R9: =IF($A9="","", IF(J9<=$F9, "Yes", "")) -> 0 | S9: =IF(R9="Yes", CEILING(MAX($G9, Q9-J9), $G9), 0) -> 0 | T9: =IFERROR(J9/(O9/30),"") -> 0
J10: =IF($A10="","", SUMIFS(Mov_Qty, Mov_Item, $A10)) -> 0 | K10: =IF($A10="","", J10 * $E10) -> 0 | L10: =IF($A10="","", SUMIFS(-Mov_Qty, Mov_Item, $A10, Mov_Type, "Consumption", Mov_Date, ">="&$V$2, Mov_Date, "<="&$W$2)) -> 0 | M10: =IF($A10="","", SUMIFS(-Mov_Qty, Mov_Item, $A10, Mov_Type, "Consumption", Mov_Date, ">="&$X$2, Mov_Date, "<="&$Y$2)) -> 0 | N10: =IF($A10="","", SUMIFS(-Mov_Qty, Mov_Item, $A10, Mov_Type, "Consumption", Mov_Date, ">="&$Z$2, Mov_Date, "<="&$AA$2)) -> 0 | O10: =IFERROR(AVERAGE(L10:N10),"") -> 0 | P10: =IF(O10>=Cfg_HiMove, "Yes", "") -> 0 | Q10: =IF($A10="","", $I10 + IFERROR(O10/30*$H10,0)) -> 0 | R10: =IF($A10="","", IF(J10<=$F10, "Yes", "")) -> 0 | S10: =IF(R10="Yes", CEILING(MAX($G10, Q10-J10), $G10), 0) -> 0 | T10: =IFERROR(J10/(O10/30),"") -> 0
J11: =IF($A11="","", SUMIFS(Mov_Qty, Mov_Item, $A11)) -> 0 | K11: =IF($A11="","", J11 * $E11) -> 0 | L11: =IF($A11="","", SUMIFS(-Mov_Qty, Mov_Item, $A11, Mov_Type, "Consumption", Mov_Date, ">="&$V$2, Mov_Date, "<="&$W$2)) -> 0 | M11: =IF($A11="","", SUMIFS(-Mov_Qty, Mov_Item, $A11, Mov_Type, "Consumption", Mov_Date, ">="&$X$2, Mov_Date, "<="&$Y$2)) -> 0 | N11: =IF($A11="","", SUMIFS(-Mov_Qty, Mov_Item, $A11, Mov_Type, "Consumption", Mov_Date, ">="&$Z$2, Mov_Date, "<="&$AA$2)) -> 0 | O11: =IFERROR(AVERAGE(L11:N11),"") -> 0 | P11: =IF(O11>=Cfg_HiMove, "Yes", "") -> 0 | Q11: =IF($A11="","", $I11 + IFERROR(O11/30*$H11,0)) -> 0 | R11: =IF($A11="","", IF(J11<=$F11, "Yes", "")) -> 0 | S11: =IF(R11="Yes", CEILING(MAX($G11, Q11-J11), $G11), 0) -> 0 | T11: =IFERROR(J11/(O11/30),"") -> 0
J12: =IF($A12="","", SUMIFS(Mov_Qty, Mov_Item, $A12)) -> 0 | K12: =IF($A12="","", J12 * $E12) -> 0 | L12: =IF($A12="","", SUMIFS(-Mov_Qty, Mov_Item, $A12, Mov_Type, "Consumption", Mov_Date, ">="&$V$2, Mov_Date, "<="&$W$2)) -> 0 | M12: =IF($A12="","", SUMIFS(-Mov_Qty, Mov_Item, $A12, Mov_Type, "Consumption", Mov_Date, ">="&$X$2, Mov_Date, "<="&$Y$2)) -> 0 | N12: =IF($A12="","", SUMIFS(-Mov_Qty, Mov_Item, $A12, Mov_Type, "Consumption", Mov_Date, ">="&$Z$2, Mov_Date, "<="&$AA$2)) -> 0 | O12: =IFERROR(AVERAGE(L12:N12),"") -> 0 | P12: =IF(O12>=Cfg_HiMove, "Yes", "") -> 0 | Q12: =IF($A12="","", $I12 + IFERROR(O12/30*$H12,0)) -> 0 | R12: =IF($A12="","", IF(J12<=$F12, "Yes", "")) -> 0 | S12: =IF(R12="Yes", CEILING(MAX($G12, Q12-J12), $G12), 0) -> 0 | T12: =IFERROR(J12/(O12/30),"") -> 0
J13: =IF($A13="","", SUMIFS(Mov_Qty, Mov_Item, $A13)) -> 0 | K13: =IF($A13="","", J13 * $E13) -> 0 | L13: =IF($A13="","", SUMIFS(-Mov_Qty, Mov_Item, $A13, Mov_Type, "Consumption", Mov_Date, ">="&$V$2, Mov_Date, "<="&$W$2)) -> 0 | M13: =IF($A13="","", SUMIFS(-Mov_Qty, Mov_Item, $A13, Mov_Type, "Consumption", Mov_Date, ">="&$X$2, Mov_Date, "<="&$Y$2)) -> 0 | N13: =IF($A13="","", SUMIFS(-Mov_Qty, Mov_Item, $A13, Mov_Type, "Consumption", Mov_Date, ">="&$Z$2, Mov_Date, "<="&$AA$2)) -> 0 | O13: =IFERROR(AVERAGE(L13:N13),"") -> 0 | P13: =IF(O13>=Cfg_HiMove, "Yes", "") -> 0 | Q13: =IF($A13="","", $I13 + IFERROR(O13/30*$H13,0)) -> 0 | R13: =IF($A13="","", IF(J13<=$F13, "Yes", "")) -> 0 | S13: =IF(R13="Yes", CEILING(MAX($G13, Q13-J13), $G13), 0) -> 0 | T13: =IFERROR(J13/(O13/30),"") -> 0
J14: =IF($A14="","", SUMIFS(Mov_Qty, Mov_Item, $A14)) -> 0 | K14: =IF($A14="","", J14 * $E14) -> 0 | L14: =IF($A14="","", SUMIFS(-Mov_Qty, Mov_Item, $A14, Mov_Type, "Consumption", Mov_Date, ">="&$V$2, Mov_Date, "<="&$W$2)) -> 0 | M14: =IF($A14="","", SUMIFS(-Mov_Qty, Mov_Item, $A14, Mov_Type, "Consumption", Mov_Date, ">="&$X$2, Mov_Date, "<="&$Y$2)) -> 0 | N14: =IF($A14="","", SUMIFS(-Mov_Qty, Mov_Item, $A14, Mov_Type, "Consumption", Mov_Date, ">="&$Z$2, Mov_Date, "<="&$AA$2)) -> 0 | O14: =IFERROR(AVERAGE(L14:N14),"") -> 0 | P14: =IF(O14>=Cfg_HiMove, "Yes", "") -> 0 | Q14: =IF($A14="","", $I14 + IFERROR(O14/30*$H14,0)) -> 0 | R14: =IF($A14="","", IF(J14<=$F14, "Yes", "")) -> 0 | S14: =IF(R14="Yes", CEILING(MAX($G14, Q14-J14), $G14), 0) -> 0 | T14: =IFERROR(J14/(O14/30),"") -> 0
J15: =IF($A15="","", SUMIFS(Mov_Qty, Mov_Item, $A15)) -> 0 | K15: =IF($A15="","", J15 * $E15) -> 0 | L15: =IF($A15="","", SUMIFS(-Mov_Qty, Mov_Item, $A15, Mov_Type, "Consumption", Mov_Date, ">="&$V$2, Mov_Date, "<="&$W$2)) -> 0 | M15: =IF($A15="","", SUMIFS(-Mov_Qty, Mov_Item, $A15, Mov_Type, "Consumption", Mov_Date, ">="&$X$2, Mov_Date, "<="&$Y$2)) -> 0 | N15: =IF($A15="","", SUMIFS(-Mov_Qty, Mov_Item, $A15, Mov_Type, "Consumption", Mov_Date, ">="&$Z$2, Mov_Date, "<="&$AA$2)) -> 0 | O15: =IFERROR(AVERAGE(L15:N15),"") -> 0 | P15: =IF(O15>=Cfg_HiMove, "Yes", "") -> 0 | Q15: =IF($A15="","", $I15 + IFERROR(O15/30*$H15,0)) -> 0 | R15: =IF($A15="","", IF(J15<=$F15, "Yes", "")) -> 0 | S15: =IF(R15="Yes", CEILING(MAX($G15, Q15-J15), $G15), 0) -> 0 | T15: =IFERROR(J15/(O15/30),"") -> 0
J16: =IF($A16="","", SUMIFS(Mov_Qty, Mov_Item, $A16)) -> 0 | K16: =IF($A16="","", J16 * $E16) -> 0 | L16: =IF($A16="","", SUMIFS(-Mov_Qty, Mov_Item, $A16, Mov_Type, "Consumption", Mov_Date, ">="&$V$2, Mov_Date, "<="&$W$2)) -> 0 | M16: =IF($A16="","", SUMIFS(-Mov_Qty, Mov_Item, $A16, Mov_Type, "Consumption", Mov_Date, ">="&$X$2, Mov_Date, "<="&$Y$2)) -> 0 | N16: =IF($A16="","", SUMIFS(-Mov_Qty, Mov_Item, $A16, Mov_Type, "Consumption", Mov_Date, ">="&$Z$2, Mov_Date, "<="&$AA$2)) -> 0 | O16: =IFERROR(AVERAGE(L16:N16),"") -> 0 | P16: =IF(O16>=Cfg_HiMove, "Yes", "") -> 0 | Q16: =IF($A16="","", $I16 + IFERROR(O16/30*$H16,0)) -> 0 | R16: =IF($A16="","", IF(J16<=$F16, "Yes", "")) -> 0 | S16: =IF(R16="Yes", CEILING(MAX($G16, Q16-J16), $G16), 0) -> 0 | T16: =IFERROR(J16/(O16/30),"") -> 0
J17: =IF($A17="","", SUMIFS(Mov_Qty, Mov_Item, $A17)) -> 0 | K17: =IF($A17="","", J17 * $E17) -> 0 | L17: =IF($A17="","", SUMIFS(-Mov_Qty, Mov_Item, $A17, Mov_Type, "Consumption", Mov_Date, ">="&$V$2, Mov_Date, "<="&$W$2)) -> 0 | M17: =IF($A17="","", SUMIFS(-Mov_Qty, Mov_Item, $A17, Mov_Type, "Consumption", Mov_Date, ">="&$X$2, Mov_Date, "<="&$Y$2)) -> 0 | N17: =IF($A17="","", SUMIFS(-Mov_Qty, Mov_Item, $A17, Mov_Type, "Consumption", Mov_Date, ">="&$Z$2, Mov_Date, "<="&$AA$2)) -> 0 | O17: =IFERROR(AVERAGE(L17:N17),"") -> 0 | P17: =IF(O17>=Cfg_HiMove, "Yes", "") -> 0 | Q17: =IF($A17="","", $I17 + IFERROR(O17/30*$H17,0)) -> 0 | R17: =IF($A17="","", IF(J17<=$F17, "Yes", "")) -> 0 | S17: =IF(R17="Yes", CEILING(MAX($G17, Q17-J17), $G17), 0) -> 0 | T17: =IFERROR(J17/(O17/30),"") -> 0
... J1004: =IF($A1004="","", SUMIFS(Mov_Qty, Mov_Item, $A1004)) -> 0 | K1004: =IF($A1004="","", J1004 * $E1004) -> 0 | L1004: =IF($A1004="","", SUMIFS(-Mov_Qty, Mov_Item, $A1004, Mov_Type, "Consumption", Mov_Date, ">="&$V$2, Mov_Date, "<="&$W$2)) -> 0 | M1004: =IF($A1004="","", SUMIFS(-Mov_Qty, Mov_Item, $A1004, Mov_Type, "Consumption", Mov_Date, ">="&$X$2, Mov_Date, "<="&$Y$2)) -> 0 | N1004: =IF($A1004="","", SUMIFS(-Mov_Qty, Mov_Item, $A1004, Mov_Type, "Consumption", Mov_Date, ">="&$Z$2, Mov_Date, "<="&$AA$2)) -> 0 | O1004: =IFERROR(AVERAGE(L1004:N1004),"") -> 0 | P1004: =IF(O1004>=Cfg_HiMove, "Yes", "") -> 0 | Q1004: =IF($A1004="","", $I1004 + IFERROR(O1004/30*$H1004,0)) -> 0 | R1004: =IF($A1004="","", IF(J1004<=$F1004, "Yes", "")) -> 0 | S1004: =IF(R1004="Yes", CEILING(MAX($G1004, Q1004-J1004), $G1004), 0) -> 0 | T1004: =IFERROR(J1004/(O1004/30),"") -> 0

Sheet Movements
A1: Date | B1: ItemID | C1: Qty | D1: Type | E1: Reference | F1: Remarks | G1: Value | H1: COGS_Value
A2: 45847 | B2: ITM-004 | C2: -461 | D2: Consumption | E2: TXN-9060 | G2: =IF($D2="", "", IF($D2="Receipt", $C2*VLOOKUP($B2, Items!$A:$E, 5, FALSE), IF($D2="Consumption", -$C2*VLOOKUP($B2, Items!$A:$E, 5, FALSE), ""))) -> 0 | H2: =IF($D2="Consumption", -$C2*VLOOKUP($B2, Items!$A:$E, 5, FALSE), 0) -> 0
A3: 45848 | B3: ITM-001 | C3: 274 | D3: Receipt | E3: TXN-7782 | G3: =IF($D3="", "", IF($D3="Receipt", $C3*VLOOKUP($B3, Items!$A:$E, 5, FALSE), IF($D3="Consumption", -$C3*VLOOKUP($B3, Items!$A:$E, 5, FALSE), ""))) -> 0 | H3: =IF($D3="Consumption", -$C3*VLOOKUP($B3, Items!$A:$E, 5, FALSE), 0) -> 0
A4: 45848 | B4: ITM-003 | C4: 31 | D4: Receipt | E4: TXN-3224 | G4: =IF($D4="", "", IF($D4="Receipt", $C4*VLOOKUP($B4, Items!$A:$E, 5, FALSE), IF($D4="Consumption", -$C4*VLOOKUP($B4, Items!$A:$E, 5, FALSE), ""))) -> 0 | H4: =IF($D4="Consumption", -$C4*VLOOKUP($B4, Items!$A:$E, 5, FALSE), 0) -> 0
A5: 45849 | B5: ITM-001 | C5: -884 | D5: Consumption | E5: TXN-7310 | G5: =IF($D5="", "", IF($D5="Receipt", $C5*VLOOKUP($B5, Items!$A:$E, 5, FALSE), IF($D5="Consumption", -$C5*VLOOKUP($B5, Items!$A:$E, 5, FALSE), ""))) -> 0 | H5: =IF($D5="Consumption", -$C5*VLOOKUP($B5, Items!$A:$E, 5, FALSE), 0) -> 0
A6: 45851 | B6: ITM-003 | C6: -468 | D6: Consumption | E6: TXN-8963 | G6: =IF($D6="", "", IF($D6="Receipt", $C6*VLOOKUP($B6, Items!$A:$E, 5, FALSE), IF($D6="Consumption", -$C6*VLOOKUP($B6, Items!$A:$E, 5, FALSE), ""))) -> 0 | H6: =IF($D6="Consumption", -$C6*VLOOKUP($B6, Items!$A:$E, 5, FALSE), 0) -> 0
A7: 45859 | B7: ITM-002 | C7: -746 | D7: Consumption | E7: TXN-3671 | G7: =IF($D7="", "", IF($D7="Receipt", $C7*VLOOKUP($B7, Items!$A:$E, 5, FALSE), IF($D7="Consumption", -$C7*VLOOKUP($B7, Items!$A:$E, 5, FALSE), ""))) -> 0 | H7: =IF($D7="Consumption", -$C7*VLOOKUP($B7, Items!$A:$E, 5, FALSE), 0) -> 0
A8: 45859 | B8: ITM-004 | C8: 730 | D8: Receipt | E8: TXN-6291 | G8: =IF($D8="", "", IF($D8="Receipt", $C8*VLOOKUP($B8, Items!$A:$E, 5, FALSE), IF($D8="Consumption", -$C8*VLOOKUP($B8, Items!$A:$E, 5, FALSE), ""))) -> 0 | H8: =IF($D8="Consumption", -$C8*VLOOKUP($B8, Items!$A:$E, 5, FALSE), 0) -> 0
A9: 45861 | B9: ITM-001 | C9: -150 | D9: Consumption | E9: TXN-6811 | G9: =IF($D9="", "", IF($D9="Receipt", $C9*VLOOKUP($B9, Items!$A:$E, 5, FALSE), IF($D9="Consumption", -$C9*VLOOKUP($B9, Items!$A:$E, 5, FALSE), ""))) -> 0 | H9: =IF($D9="Consumption", -$C9*VLOOKUP($B9, Items!$A:$E, 5, FALSE), 0) -> 0
A10: 45862 | B10: ITM-003 | C10: -800 | D10: Consumption | E10: TXN-4006 | G10: =IF($D10="", "", IF($D10="Receipt", $C10*VLOOKUP($B10, Items!$A:$E, 5, FALSE), IF($D10="Consumption", -$C10*VLOOKUP($B10, Items!$A:$E, 5, FALSE), ""))) -> 0 | H10: =IF($D10="Consumption", -$C10*VLOOKUP($B10, Items!$A:$E, 5, FALSE), 0) -> 0
A11: 45865 | B11: ITM-002 | C11: 737 | D11: Receipt | E11: TXN-4129 | G11: =IF($D11="", "", IF($D11="Receipt", $C11*VLOOKUP($B11, Items!$A:$E, 5, FALSE), IF($D11="Consumption", -$C11*VLOOKUP($B11, Items!$A:$E, 5, FALSE), ""))) -> 0 | H11: =IF($D11="Consumption", -$C11*VLOOKUP($B11, Items!$A:$E, 5, FALSE), 0) -> 0
A12: 45865 | B12: ITM-002 | C12: 698 | D12: Receipt | E12: TXN-8496 | G12: =IF($D12="", "", IF($D12="Receipt", $C12*VLOOKUP($B12, Items!$A:$E, 5, FALSE), IF($D12="Consumption", -$C12*VLOOKUP($B12, Items!$A:$E, 5, FALSE), ""))) -> 0 | H12: =IF($D12="Consumption", -$C12*VLOOKUP($B12, Items!$A:$E, 5, FALSE), 0) -> 0
A13: 45869 | B13: ITM-004 | C13: -153 | D13: Consumption | E13: TXN-4025 | G13: =IF($D13="", "", IF($D13="Receipt", $C13*VLOOKUP($B13, Items!$A:$E, 5, FALSE), IF($D13="Consumption", -$C13*VLOOKUP($B13, Items!$A:$E, 5, FALSE), ""))) -> 0 | H13: =IF($D13="Consumption", -$C13*VLOOKUP($B13, Items!$A:$E, 5, FALSE), 0) -> 0
... A53: 45957 | B53: ITM-001 | C53: -665 | D53: Consumption | E53: TXN-3310 | G53: =IF($D53="", "", IF($D53="Receipt", $C53*VLOOKUP($B53, Items!$A:$E, 5, FALSE), IF($D53="Consumption", -$C53*VLOOKUP($B53, Items!$A:$E, 5, FALSE), ""))) -> 0 | H53: =IF($D53="Consumption", -$C53*VLOOKUP($B53, Items!$A:$E, 5, FALSE), 0) -> 0
G54: =IF($D54="", "", IF($D54="Receipt", $C54*VLOOKUP($B54, Items!$A:$E, 5, FALSE), IF($D54="Consumption", -$C54*VLOOKUP($B54, Items!$A:$E, 5, FALSE), ""))) -> 0 | H54: =IF($D54="Consumption", -$C54*VLOOKUP($B54, Items!$A:$E, 5, FALSE), 0) -> 0
G55: =IF($D55="", "", IF($D55="Receipt", $C55*VLOOKUP($B55, Items!$A:$E, 5, FALSE), IF($D55="Consumption", -$C55*VLOOKUP($B55, Items!$A:$E, 5, FALSE), ""))) -> 0 | H55: =IF($D55="Consumption", -$C55*VLOOKUP($B55, Items!$A:$E, 5, FALSE), 0) -> 0
G56: =IF($D56="", "", IF($D56="Receipt", $C56*VLOOKUP($B56, Items!$A:$E, 5, FALSE), IF($D56="Consumption", -$C56*VLOOKUP($B56, Items!$A:$E, 5, FALSE), ""))) -> 0 | H56: =IF($D56="Consumption", -$C56*VLOOKUP($B56, Items!$A:$E, 5, FALSE), 0) -> 0
G57: =IF($D57="", "", IF($D57="Receipt", $C57*VLOOKUP($B57, Items!$A:$E, 5, FALSE), IF($D57="Consumption", -$C57*VLOOKUP($B57, Items!$A:$E, 5, FALSE), ""))) -> 0 | H57: =IF($D57="Consumption", -$C57*VLOOKUP($B57, Items!$A:$E, 5, FALSE), 0) -> 0
G58: =IF($D58="", "", IF($D58="Receipt", $C58*VLOOKUP($B58, Items!$A:$E, 5, FALSE), IF($D58="Consumption", -$C58*VLOOKUP($B58, Items!$A:$E, 5, FALSE), ""))) -> 0 | H58: =IF($D58="Consumption", -$C58*VLOOKUP($B58, Items!$A:$E, 5, FALSE), 0) -> 0
G59: =IF($D59="", "", IF($D59="Receipt", $C59*VLOOKUP($B59, Items!$A:$E, 5, FALSE), IF($D59="Consumption", -$C59*VLOOKUP($B59, Items!$A:$E, 5, FALSE), ""))) -> 0 | H59: =IF($D59="Consumption", -$C59*VLOOKUP($B59, Items!$A:$E, 5, FALSE), 0) -> 0
G60: =IF($D60="", "", IF($D60="Receipt", $C60*VLOOKUP($B60, Items!$A:$E, 5, FALSE), IF($D60="Consumption", -$C60*VLOOKUP($B60, Items!$A:$E, 5, FALSE), ""))) -> 0 | H60: =IF($D60="Consumption", -$C60*VLOOKUP($B60, Items!$A:$E, 5, FALSE), 0) -> 0
G61: =IF($D61="", "", IF($D61="Receipt", $C61*VLOOKUP($B61, Items!$A:$E, 5, FALSE), IF($D61="Consumption", -$C61*VLOOKUP($B61, Items!$A:$E, 5, FALSE), ""))) -> 0 | H61: =IF($D61="Consumption", -$C61*VLOOKUP($B61, Items!$A:$E, 5, FALSE), 0) -> 0
G62: =IF($D62="", "", IF($D62="Receipt", $C62*VLOOKUP($B62, Items!$A:$E, 5, FALSE), IF($D62="Consumption", -$C62*VLOOKUP($B62, Items!$A:$E, 5, FALSE), ""))) -> 0 | H62: =IF($D62="Consumption", -$C62*VLOOKUP($B62, Items!$A:$E, 5, FALSE), 0) -> 0
G63: =IF($D63="", "", IF($D63="Receipt", $C63*VLOOKUP($B63, Items!$A:$E, 5, FALSE), IF($D63="Consumption", -$C63*VLOOKUP($B63, Items!$A:$E, 5, FALSE), ""))) -> 0 | H63: =IF($D63="Consumption", -$C63*VLOOKUP($B63, Items!$A:$E, 5, FALSE), 0) -> 0
G64: =IF($D64="", "", IF($D64="Receipt", $C64*VLOOKUP($B64, Items!$A:$E, 5, FALSE), IF($D64="Consumption", -$C64*VLOOKUP($B64, Items!$A:$E, 5, FALSE), ""))) -> 0 | H64: =IF($D64="Consumption", -$C64*VLOOKUP($B64, Items!$A:$E, 5, FALSE), 0) -> 0
G65: =IF($D65="", "", IF($D65="Receipt", $C65*VLOOKUP($B65, Items!$A:$E, 5, FALSE), IF($D65="Consumption", -$C65*VLOOKUP($B65, Items!$A:$E, 5, FALSE), ""))) -> 0 | H65: =IF($D65="Consumption", -$C65*VLOOKUP($B65, Items!$A:$E, 5, FALSE), 0) -> 0
... G2052: =IF($D2052="", "", IF($D2052="Receipt", $C2052*VLOOKUP($B2052, Items!$A:$E, 5, FALSE), IF($D2052="Consumption", -$C2052*VLOOKUP($B2052, Items!$A:$E, 5, FALSE), ""))) -> 0 | H2052: =IF($D2052="Consumption", -$C2052*VLOOKUP($B2052, Items!$A:$E, 5, FALSE), 0) -> 0

Sheet Sales
A1: Date | B1: ItemID | C1: Qty | D1: UnitPrice | E1: Amount
A2: 45877 | B2: ITM-004 | C2: 1 | D2: 7.0078806 | E2: 7.0078806
A3: 45880 | B3: ITM-002 | C3: 22 | D3: 1078.9269 | E3: 23736.393
A4: 45896 | B4: ITM-001 | C4: 8 | D4: 260.41762 | E4: 2083.341
A5: 45902 | B5: ITM-001 | C5: 24 | D5: 334.96334 | E5: 8039.1202
A6: 45905 | B6: ITM-001 | C6: 5 | D6: 288.83563 | E6: 1444.1782
A7: 45912 | B7: ITM-001 | C7: 7 | D7: 330.22154 | E7: 2311.5508
A8: 45921 | B8: ITM-001 | C8: 7 | D8: 237.59154 | E8: 1663.1408
A9: 45922 | B9: ITM-003 | C9: 24 | D9: 2638.456 | E9: 63322.944
A10: 45924 | B10: ITM-001 | C10: 21 | D10: 272.18085 | E10: 5715.7978
A11: 45925 | B11: ITM-001 | C11: 5 | D11: 273.75718 | E11: 1368.7859
A12: 45926 | B12: ITM-002 | C12: 21 | D12: 1489.4097 | E12: 31277.604
A13: 45932 | B13: ITM-002 | C13: 7 | D13: 1177.4602 | E13: 8242.2213
... A19: 45963 | B19: ITM-002 | C19: 15 | D19: 1375.264 | E19: 20628.961

Sheet Config
A1: Key | B1: Value
A2: Today | B2: 45964
A3: BaselineDate | B3: 45846
A4: BaselineOpeningValue | B4: 0
A5: HighMovingMonthlyThreshold | B5: 1000
A6: CoverageWarnDays | B6: 30

Sheet PnL_Daily
A1: Date | B1: OpeningValue | C1: Purchases | D1: ClosingValue | E1: COGS_Periodic | F1: Revenue | G1: GrossProfit
A2: 45905 | B2: =Cfg_BaselineOpeningValue + SUMIFS(Mov_Value, Mov_Date, ">"&Cfg_BaselineDate, Mov_Date, "<"&$A2) -> 0 | C2: =SUMIFS(Mov_Value, Mov_Type, "Receipt", Mov_Date, $A2) -> 0 | D2: =Cfg_BaselineOpeningValue + SUMIFS(Mov_Value, Mov_Date, ">"&Cfg_BaselineDate, Mov_Date, "<="&$A2) -> 0 | E2: =B2+C2-D2 -> 0 | F2: =SUMIFS(Sales_Amount, Sales_Date, $A2) -> 0 | G2: =F2-E2 -> 0
A3: 45906 | B3: =Cfg_BaselineOpeningValue + SUMIFS(Mov_Value, Mov_Date, ">"&Cfg_BaselineDate, Mov_Date, "<"&$A3) -> 0 | C3: =SUMIFS(Mov_Value, Mov_Type, "Receipt", Mov_Date, $A3) -> 0 | D3: =Cfg_BaselineOpeningValue + SUMIFS(Mov_Value, Mov_Date, ">"&Cfg_BaselineDate, Mov_Date, "<="&$A3) -> 0 | E3: =B3+C3-D3 -> 0 | F3: =SUMIFS(Sales_Amount, Sales_Date, $A3) -> 0 | G3: =F3-E3 -> 0
A4: 45907 | B4: =Cfg_BaselineOpeningValue + SUMIFS(Mov_Value, Mov_Date, ">"&Cfg_BaselineDate, Mov_Date, "<"&$A4) -> 0 | C4: =SUMIFS(Mov_Value, Mov_Type, "Receipt", Mov_Date, $A4) -> 0 | D4: =Cfg_BaselineOpeningValue + SUMIFS(Mov_Value, Mov_Date, ">"&Cfg_BaselineDate, Mov_Date, "<="&$A4) -> 0 | E4: =B4+C4-D4 -> 0 | F4: =SUMIFS(Sales_Amount, Sales_Date, $A4) -> 0 | G4: =F4-E4 -> 0
A5: 45908 | B5: =Cfg_BaselineOpeningValue + SUMIFS(Mov_Value, Mov_Date, ">"&Cfg_BaselineDate, Mov_Date, "<"&$A5) -> 0 | C5: =SUMIFS(Mov_Value, Mov_Type, "Receipt", Mov_Date, $A5) -> 0 | D5: =Cfg_BaselineOpeningValue + SUMIFS(Mov_Value, Mov_Date, ">"&Cfg_BaselineDate, Mov_Date, "<="&$A5) -> 0 | E5: =B5+C5-D5 -> 0 | F5: =SUMIFS(Sales_Amount, Sales_Date, $A5) -> 0 | G5: =F5-E5 -> 0
A6: 45909 | B6: =Cfg_BaselineOpeningValue + SUMIFS(Mov_Value, Mov_Date, ">"&Cfg_BaselineDate, Mov_Date, "<"&$A6) -> 0 | C6: =SUMIFS(Mov_Value, Mov_Type, "Receipt", Mov_Date, $A6) -> 0 | D6: =Cfg_BaselineOpeningValue + SUMIFS(Mov_Value, Mov_Date, ">"&Cfg_BaselineDate, Mov_Date, "<="&$A6) -> 0 | E6: =B6+C6-D6 -> 0 | F6: =SUMIFS(Sales_Amount, Sales_Date, $A6) -> 0 | G6: =F6-E6 -> 0
A7: 45910 | B7: =Cfg_BaselineOpeningValue + SUMIFS(Mov_Value, Mov_Date, ">"&Cfg_BaselineDate, Mov_Date, "<"&$A7) -> 0 | C7: =SUMIFS(Mov_Value, Mov_Type, "Receipt", Mov_Date, $A7) -> 0 | D7: =Cfg_BaselineOpeningValue + SUMIFS(Mov_Value, Mov_Date, ">"&Cfg_BaselineDate, Mov_Date, "<="&$A7) -> 0 | E7: =B7+C7-D7 -> 0 | F7: =SUMIFS(Sales_Amount, Sales_Date, $A7) -> 0 | G7: =F7-E7 -> 0
A8: 45911 | B8: =Cfg_BaselineOpeningValue + SUMIFS(Mov_Value, Mov_Date, ">"&Cfg_BaselineDate, Mov_Date, "<"&$A8) -> 0 | C8: =SUMIFS(Mov_Value, Mov_Type, "Receipt", Mov_Date, $A8) -> 0 | D8: =Cfg_BaselineOpeningValue + SUMIFS(Mov_Value, Mov_Date, ">"&Cfg_BaselineDate, Mov_Date, "<="&$A8) -> 0 | E8: =B8+C8-D8 -> 0 | F8: =SUMIFS(Sales_Amount, Sales_Date, $A8) -> 0 | G8: =F8-E8 -> 0
A9: 45912 | B9: =Cfg_BaselineOpeningValue + SUMIFS(Mov_Value, Mov_Date, ">"&Cfg_BaselineDate, Mov_Date, "<"&$A9) -> 0 | C9: =SUMIFS(Mov_Value, Mov_Type, "Receipt", Mov_Date, $A9) -> 0 | D9: =Cfg_BaselineOpeningValue + SUMIFS(Mov_Value, Mov_Date, ">"&Cfg_BaselineDate, Mov_Date, "<="&$A9) -> 0 | E9: =B9+C9-D9 -> 0 | F9: =SUMIFS(Sales_Amount, Sales_Date, $A9) -> 0 | G9: =F9-E9 -> 0
A10: 45913 | B10: =Cfg_BaselineOpeningValue + SUMIFS(Mov_Value, Mov_Date, ">"&Cfg_BaselineDate, Mov_Date, "<"&$A10) -> 0 | C10: =SUMIFS(Mov_Value, Mov_Type, "Receipt", Mov_Date, $A10) -> 0 | D10: =Cfg_BaselineOpeningValue + SUMIFS(Mov_Value, Mov_Date, ">"&Cfg_BaselineDate, Mov_Date, "<="&$A10) -> 0 | E10: =B10+C10-D10 -> 0 | F10: =SUMIFS(Sales_Amount, Sales_Date, $A10) -> 0 | G10: =F10-E10 -> 0
A11: 45914 | B11: =Cfg_BaselineOpeningValue + SUMIFS(Mov_Value, Mov_Date, ">"&Cfg_BaselineDate, Mov_Date, "<"&$A11) -> 0 | C11: =SUMIFS(Mov_Value, Mov_Type, "Receipt", Mov_Date, $A11) -> 0 | D11: =Cfg_BaselineOpeningValue + SUMIFS(Mov_Value, Mov_Date, ">"&Cfg_BaselineDate, Mov_Date, "<="&$A11) -> 0 | E11: =B11+C11-D11 -> 0 | F11: =SUMIFS(Sales_Amount, Sales_Date, $A11) -> 0 | G11: =F11-E11 -> 0
A12: 45915 | B12: =Cfg_BaselineOpeningValue + SUMIFS(Mov_Value, Mov_Date, ">"&Cfg_BaselineDate, Mov_Date, "<"&$A12) -> 0 | C12: =SUMIFS(Mov_Value, Mov_Type, "Receipt", Mov_Date, $A12) -> 0 | D12: =Cfg_BaselineOpeningValue + SUMIFS(Mov_Value, Mov_Date, ">"&Cfg_BaselineDate, Mov_Date, "<="&$A12) -> 0 | E12: =B12+C12-D12 -> 0 | F12: =SUMIFS(Sales_Amount, Sales_Date, $A12) -> 0 | G12: =F12-E12 -> 0
A13: 45916 | B13: =Cfg_BaselineOpeningValue + SUMIFS(Mov_Value, Mov_Date, ">"&Cfg_BaselineDate, Mov_Date, "<"&$A13) -> 0 | C13: =SUMIFS(Mov_Value, Mov_Type, "Receipt", Mov_Date, $A13) -> 0 | D13: =Cfg_BaselineOpeningValue + SUMIFS(Mov_Value, Mov_Date, ">"&Cfg_BaselineDate, Mov_Date, "<="&$A13) -> 0 | E13: =B13+C13-D13 -> 0 | F13: =SUMIFS(Sales_Amount, Sales_Date, $A13) -> 0 | G13: =F13-E13 -> 0
... A61: 45964 | B61: =Cfg_BaselineOpeningValue + SUMIFS(Mov_Value, Mov_Date, ">"&Cfg_BaselineDate, Mov_Date, "<"&$A61) -> 0 | C61: =SUMIFS(Mov_Value, Mov_Type, "Receipt", Mov_Date, $A61) -> 0 | D61: =Cfg_BaselineOpeningValue + SUMIFS(Mov_Value, Mov_Date, ">"&Cfg_BaselineDate, Mov_Date, "<="&$A61) -> 0 | E61: =B61+C61-D61 -> 0 | F61: =SUMIFS(Sales_Amount, Sales_Date, $A61) -> 0 | G61: =F61-E61 -> 0

Sheet PnL_Weekly
A1: StartDate | B1: EndDate | C1: Label | D1: OpeningValue | E1: Purchases | F1: ClosingValue | G1: COGS_Periodic | H1: Revenue | I1: GrossProfit
A2: 45887 | B2: 45893 | C2: Wk 34 (18-Aug–24-Aug) | D2: =Cfg_BaselineOpeningValue + SUMIFS(Mov_Value, Mov_Date, ">"&Cfg_BaselineDate, Mov_Date, "<"&$A2) -> 0 | E2: =SUMIFS(Mov_Value, Mov_Type, "Receipt", Mov_Date, ">="&$A2, Mov_Date, "<="&$B2) -> 0 | F2: =Cfg_BaselineOpeningValue + SUMIFS(Mov_Value, Mov_Date, ">"&Cfg_BaselineDate, Mov_Date, "<="&$B2) -> 0 | G2: =D2+E2-F2 -> 0 | H2: =SUMIFS(Sales_Amount, Sales_Date, ">="&$A2, Sales_Date, "<="&$B2) -> 0 | I2: =H2-G2 -> 0
A3: 45894 | B3: 45900 | C3: Wk 35 (25-Aug–31-Aug) | D3: =Cfg_BaselineOpeningValue + SUMIFS(Mov_Value, Mov_Date, ">"&Cfg_BaselineDate, Mov_Date, "<"&$A3) -> 0 | E3: =SUMIFS(Mov_Value, Mov_Type, "Receipt", Mov_Date, ">="&$A3, Mov_Date, "<="&$B3) -> 0 | F3: =Cfg_BaselineOpeningValue + SUMIFS(Mov_Value, Mov_Date, ">"&Cfg_BaselineDate, Mov_Date, "<="&$B3) -> 0 | G3: =D3+E3-F3 -> 0 | H3: =SUMIFS(Sales_Amount, Sales_Date, ">="&$A3, Sales_Date, "<="&$B3) -> 0 | I3: =H3-G3 -> 0
A4: 45901 | B4: 45907 | C4: Wk 36 (01-Sep–07-Sep) | D4: =Cfg_BaselineOpeningValue + SUMIFS(Mov_Value, Mov_Date, ">"&Cfg_BaselineDate, Mov_Date, "<"&$A4) -> 0 | E4: =SUMIFS(Mov_Value, Mov_Type, "Receipt", Mov_Date, ">="&$A4, Mov_Date, "<="&$B4) -> 0 | F4: =Cfg_BaselineOpeningValue + SUMIFS(Mov_Value, Mov_Date, ">"&Cfg_BaselineDate, Mov_Date, "<="&$B4) -> 0 | G4: =D4+E4-F4 -> 0 | H4: =SUMIFS(Sales_Amount, Sales_Date, ">="&$A4, Sales_Date, "<="&$B4) -> 0 | I4: =H4-G4 -> 0
A5: 45908 | B5: 45914 | C5: Wk 37 (08-Sep–14-Sep) | D5: =Cfg_BaselineOpeningValue + SUMIFS(Mov_Value, Mov_Date, ">"&Cfg_BaselineDate, Mov_Date, "<"&$A5) -> 0 | E5: =SUMIFS(Mov_Value, Mov_Type, "Receipt", Mov_Date, ">="&$A5, Mov_Date, "<="&$B5) -> 0 | F5: =Cfg_BaselineOpeningValue + SUMIFS(Mov_Value, Mov_Date, ">"&Cfg_BaselineDate, Mov_Date, "<="&$B5) -> 0 | G5: =D5+E5-F5 -> 0 | H5: =SUMIFS(Sales_Amount, Sales_Date, ">="&$A5, Sales_Date, "<="&$B5) -> 0 | I5: =H5-G5 -> 0
A6: 45915 | B6: 45921 | C6: Wk 38 (15-Sep–21-Sep) | D6: =Cfg_BaselineOpeningValue + SUMIFS(Mov_Value, Mov_Date, ">"&Cfg_BaselineDate, Mov_Date, "<"&$A6) -> 0 | E6: =SUMIFS(Mov_Value, Mov_Type, "Receipt", Mov_Date, ">="&$A6, Mov_Date, "<="&$B6) -> 0 | F6: =Cfg_BaselineOpeningValue + SUMIFS(Mov_Value, Mov_Date, ">"&Cfg_BaselineDate, Mov_Date, "<="&$B6) -> 0 | G6: =D6+E6-F6 -> 0 | H6: =SUMIFS(Sales_Amount, Sales_Date, ">="&$A6, Sales_Date, "<="&$B6) -> 0 | I6: =H6-G6 -> 0
A7: 45922 | B7: 45928 | C7: Wk 39 (22-Sep–28-Sep) | D7: =Cfg_BaselineOpeningValue + SUMIFS(Mov_Value, Mov_Date, ">"&Cfg_BaselineDate, Mov_Date, "<"&$A7) -> 0 | E7: =SUMIFS(Mov_Value, Mov_Type, "Receipt", Mov_Date, ">="&$A7, Mov_Date, "<="&$B7) -> 0 | F7: =Cfg_BaselineOpeningValue + SUMIFS(Mov_Value, Mov_Date, ">"&Cfg_BaselineDate, Mov_Date, "<="&$B7) -> 0 | G7: =D7+E7-F7 -> 0 | H7: =SUMIFS(Sales_Amount, Sales_Date, ">="&$A7, Sales_Date, "<="&$B7) -> 0 | I7: =H7-G7 -> 0
A8: 45929 | B8: 45935 | C8: Wk 40 (29-Sep–05-Oct) | D8: =Cfg_BaselineOpeningValue + SUMIFS(Mov_Value, Mov_Date, ">"&Cfg_BaselineDate, Mov_Date, "<"&$A8) -> 0 | E8: =SUMIFS(Mov_Value, Mov_Type, "Receipt", Mov_Date, ">="&$A8, Mov_Date, "<="&$B8) -> 0 | F8: =Cfg_BaselineOpeningValue + SUMIFS(Mov_Value, Mov_Date, ">"&Cfg_BaselineDate, Mov_Date, "<="&$B8) -> 0 | G8: =D8+E8-F8 -> 0 | H8: =SUMIFS(Sales_Amount, Sales_Date, ">="&$A8, Sales_Date, "<="&$B8) -> 0 | I8: =H8-G8 -> 0
A9: 45936 | B9: 45942 | C9: Wk 41 (06-Oct–12-Oct) | D9: =Cfg_BaselineOpeningValue + SUMIFS(Mov_Value, Mov_Date, ">"&Cfg_BaselineDate, Mov_Date, "<"&$A9) -> 0 | E9: =SUMIFS(Mov_Value, Mov_Type, "Receipt", Mov_Date, ">="&$A9, Mov_Date, "<="&$B9) -> 0 | F9: =Cfg_BaselineOpeningValue + SUMIFS(Mov_Value, Mov_Date, ">"&Cfg_BaselineDate, Mov_Date, "<="&$B9) -> 0 | G9: =D9+E9-F9 -> 0 | H9: =SUMIFS(Sales_Amount, Sales_Date, ">="&$A9, Sales_Date, "<="&$B9) -> 0 | I9: =H9-G9 -> 0
A10: 45943 | B10: 45949 | C10: Wk 42 (13-Oct–19-Oct) | D10: =Cfg_BaselineOpeningValue + SUMIFS(Mov_Value, Mov_Date, ">"&Cfg_BaselineDate, Mov_Date, "<"&$A10) -> 0 | E10: =SUMIFS(Mov_Value, Mov_Type, "Receipt", Mov_Date, ">="&$A10, Mov_Date, "<="&$B10) -> 0 | F10: =Cfg_BaselineOpeningValue + SUMIFS(Mov_Value, Mov_Date, ">"&Cfg_BaselineDate, Mov_Date, "<="&$B10) -> 0 | G10: =D10+E10-F10 -> 0 | H10: =SUMIFS(Sales_Amount, Sales_Date, ">="&$A10, Sales_Date, "<="&$B10) -> 0 | I10: =H10-G10 -> 0
A11: 45950 | B11: 45956 | C11: Wk 43 (20-Oct–26-Oct) | D11: =Cfg_BaselineOpeningValue + SUMIFS(Mov_Value, Mov_Date, ">"&Cfg_BaselineDate, Mov_Date, "<"&$A11) -> 0 | E11: =SUMIFS(Mov_Value, Mov_Type, "Receipt", Mov_Date, ">="&$A11, Mov_Date, "<="&$B11) -> 0 | F11: =Cfg_BaselineOpeningValue + SUMIFS(Mov_Value, Mov_Date, ">"&Cfg_BaselineDate, Mov_Date, "<="&$B11) -> 0 | G11: =D11+E11-F11 -> 0 | H11: =SUMIFS(Sales_Amount, Sales_Date, ">="&$A11, Sales_Date, "<="&$B11) -> 0 | I11: =H11-G11 -> 0
A12: 45957 | B12: 45963 | C12: Wk 44 (27-Oct–02-Nov) | D12: =Cfg_BaselineOpeningValue + SUMIFS(Mov_Value, Mov_Date, ">"&Cfg_BaselineDate, Mov_Date, "<"&$A12) -> 0 | E12: =SUMIFS(Mov_Value, Mov_Type, "Receipt", Mov_Date, ">="&$A12, Mov_Date, "<="&$B12) -> 0 | F12: =Cfg_BaselineOpeningValue + SUMIFS(Mov_Value, Mov_Date, ">"&Cfg_BaselineDate, Mov_Date, "<="&$B12) -> 0 | G12: =D12+E12-F12 -> 0 | H12: =SUMIFS(Sales_Amount, Sales_Date, ">="&$A12, Sales_Date, "<="&$B12) -> 0 | I12: =H12-G12 -> 0
A13: 45964 | B13: 45970 | C13: Wk 45 (03-Nov–09-Nov) | D13: =Cfg_BaselineOpeningValue + SUMIFS(Mov_Value, Mov_Date, ">"&Cfg_BaselineDate, Mov_Date, "<"&$A13) -> 0 | E13: =SUMIFS(Mov_Value, Mov_Type, "Receipt", Mov_Date, ">="&$A13, Mov_Date, "<="&$B13) -> 0 | F13: =Cfg_BaselineOpeningValue + SUMIFS(Mov_Value, Mov_Date, ">"&Cfg_BaselineDate, Mov_Date, "<="&$B13) -> 0 | G13: =D13+E13-F13 -> 0 | H13: =SUMIFS(Sales_Amount, Sales_Date, ">="&$A13, Sales_Date, "<="&$B13) -> 0 | I13: =H13-G13 -> 0

Sheet PnL_Monthly
A1: StartDate | B1: EndDate | C1: Label | D1: OpeningValue | E1: Purchases | F1: ClosingValue | G1: COGS_Periodic | H1: Revenue | I1: GrossProfit
A2: 45627 | B2: 45657 | C2: Dec 2024 | D2: =Cfg_BaselineOpeningValue + SUMIFS(Mov_Value, Mov_Date, ">"&Cfg_BaselineDate, Mov_Date, "<"&$A2) -> 0 | E2: =SUMIFS(Mov_Value, Mov_Type, "Receipt", Mov_Date, ">="&$A2, Mov_Date, "<="&$B2) -> 0 | F2: =Cfg_BaselineOpeningValue + SUMIFS(Mov_Value, Mov_Date, ">"&Cfg_BaselineDate, Mov_Date, "<="&$B2) -> 0 | G2: =D2+E2-F2 -> 0 | H2: =SUMIFS(Sales_Amount, Sales_Date, ">="&$A2, Sales_Date, "<="&$B2) -> 0 | I2: =H2-G2 -> 0
A3: 45658 | B3: 45688 | C3: Jan 2025 | D3: =Cfg_BaselineOpeningValue + SUMIFS(Mov_Value, Mov_Date, ">"&Cfg_BaselineDate, Mov_Date, "<"&$A3) -> 0 | E3: =SUMIFS(Mov_Value, Mov_Type, "Receipt", Mov_Date, ">="&$A3, Mov_Date, "<="&$B3) -> 0 | F3: =Cfg_BaselineOpeningValue + SUMIFS(Mov_Value, Mov_Date, ">"&Cfg_BaselineDate, Mov_Date, "<="&$B3) -> 0 | G3: =D3+E3-F3 -> 0 | H3: =SUMIFS(Sales_Amount, Sales_Date, ">="&$A3, Sales_Date, "<="&$B3) -> 0 | I3: =H3-G3 -> 0
A4: 45689 | B4: 45716 | C4: Feb 2025 | D4: =Cfg_BaselineOpeningValue + SUMIFS(Mov_Value, Mov_Date, ">"&Cfg_BaselineDate, Mov_Date, "<"&$A4) -> 0 | E4: =SUMIFS(Mov_Value, Mov_Type, "Receipt", Mov_Date, ">="&$A4, Mov_Date, "<="&$B4) -> 0 | F4: =Cfg_BaselineOpeningValue + SUMIFS(Mov_Value, Mov_Date, ">"&Cfg_BaselineDate, Mov_Date, "<="&$B4) -> 0 | G4: =D4+E4-F4 -> 0 | H4: =SUMIFS(Sales_Amount, Sales_Date, ">="&$A4, Sales_Date, "<="&$B4) -> 0 | I4: =H4-G4 -> 0
A5: 45717 | B5: 45747 | C5: Mar 2025 | D5: =Cfg_BaselineOpeningValue + SUMIFS(Mov_Value, Mov_Date, ">"&Cfg_BaselineDate, Mov_Date, "<"&$A5) -> 0 | E5: =SUMIFS(Mov_Value, Mov_Type, "Receipt", Mov_Date, ">="&$A5, Mov_Date, "<="&$B5) -> 0 | F5: =Cfg_BaselineOpeningValue + SUMIFS(Mov_Value, Mov_Date, ">"&Cfg_BaselineDate, Mov_Date, "<="&$B5) -> 0 | G5: =D5+E5-F5 -> 0 | H5: =SUMIFS(Sales_Amount, Sales_Date, ">="&$A5, Sales_Date, "<="&$B5) -> 0 | I5: =H5-G5 -> 0
A6: 45748 | B6: 45777 | C6: Apr 2025 | D6: =Cfg_BaselineOpeningValue + SUMIFS(Mov_Value, Mov_Date, ">"&Cfg_BaselineDate, Mov_Date, "<"&$A6) -> 0 | E6: =SUMIFS(Mov_Value, Mov_Type, "Receipt", Mov_Date, ">="&$A6, Mov_Date, "<="&$B6) -> 0 | F6: =Cfg_BaselineOpeningValue + SUMIFS(Mov_Value, Mov_Date, ">"&Cfg_BaselineDate, Mov_Date, "<="&$B6) -> 0 | G6: =D6+E6-F6 -> 0 | H6: =SUMIFS(Sales_Amount, Sales_Date, ">="&$A6, Sales_Date, "<="&$B6) -> 0 | I6: =H6-G6 -> 0
A7: 45778 | B7: 45808 | C7: May 2025 | D7: =Cfg_BaselineOpeningValue + SUMIFS(Mov_Value, Mov_Date, ">"&Cfg_BaselineDate, Mov_Date, "<"&$A7) -> 0 | E7: =SUMIFS(Mov_Value, Mov_Type, "Receipt", Mov_Date, ">="&$A7, Mov_Date, "<="&$B7) -> 0 | F7: =Cfg_BaselineOpeningValue + SUMIFS(Mov_Value, Mov_Date, ">"&Cfg_BaselineDate, Mov_Date, "<="&$B7) -> 0 | G7: =D7+E7-F7 -> 0 | H7: =SUMIFS(Sales_Amount, Sales_Date, ">="&$A7, Sales_Date, "<="&$B7) -> 0 | I7: =H7-G7 -> 0
A8: 45809 | B8: 45838 | C8: Jun 2025 | D8: =Cfg_BaselineOpeningValue + SUMIFS(Mov_Value, Mov_Date, ">"&Cfg_BaselineDate, Mov_Date, "<"&$A8) -> 0 | E8: =SUMIFS(Mov_Value, Mov_Type, "Receipt", Mov_Date, ">="&$A8, Mov_Date, "<="&$B8) -> 0 | F8: =Cfg_BaselineOpeningValue + SUMIFS(Mov_Value, Mov_Date, ">"&Cfg_BaselineDate, Mov_Date, "<="&$B8) -> 0 | G8: =D8+E8-F8 -> 0 | H8: =SUMIFS(Sales_Amount, Sales_Date, ">="&$A8, Sales_Date, "<="&$B8) -> 0 | I8: =H8-G8 -> 0
A9: 45839 | B9: 45869 | C9: Jul 2025 | D9: =Cfg_BaselineOpeningValue + SUMIFS(Mov_Value, Mov_Date, ">"&Cfg_BaselineDate, Mov_Date, "<"&$A9) -> 0 | E9: =SUMIFS(Mov_Value, Mov_Type, "Receipt", Mov_Date, ">="&$A9, Mov_Date, "<="&$B9) -> 0 | F9: =Cfg_BaselineOpeningValue + SUMIFS(Mov_Value, Mov_Date, ">"&Cfg_BaselineDate, Mov_Date, "<="&$B9) -> 0 | G9: =D9+E9-F9 -> 0 | H9: =SUMIFS(Sales_Amount, Sales_Date, ">="&$A9, Sales_Date, "<="&$B9) -> 0 | I9: =H9-G9 -> 0
A10: 45870 | B10: 45900 | C10: Aug 2025 | D10: =Cfg_BaselineOpeningValue + SUMIFS(Mov_Value, Mov_Date, ">"&Cfg_BaselineDate, Mov_Date, "<"&$A10) -> 0 | E10: =SUMIFS(Mov_Value, Mov_Type, "Receipt", Mov_Date, ">="&$A10, Mov_Date, "<="&$B10) -> 0 | F10: =Cfg_BaselineOpeningValue + SUMIFS(Mov_Value, Mov_Date, ">"&Cfg_BaselineDate, Mov_Date, "<="&$B10) -> 0 | G10: =D10+E10-F10 -> 0 | H10: =SUMIFS(Sales_Amount, Sales_Date, ">="&$A10, Sales_Date, "<="&$B10) -> 0 | I10: =H10-G10 -> 0
A11: 45901 | B11: 45930 | C11: Sep 2025 | D11: =Cfg_BaselineOpeningValue + SUMIFS(Mov_Value, Mov_Date, ">"&Cfg_BaselineDate, Mov_Date, "<"&$A11) -> 0 | E11: =SUMIFS(Mov_Value, Mov_Type, "Receipt", Mov_Date, ">="&$A11, Mov_Date, "<="&$B11) -> 0 | F11: =Cfg_BaselineOpeningValue + SUMIFS(Mov_Value, Mov_Date, ">"&Cfg_BaselineDate, Mov_Date, "<="&$B11) -> 0 | G11: =D11+E11-F11 -> 0 | H11: =SUMIFS(Sales_Amount, Sales_Date, ">="&$A11, Sales_Date, "<="&$B11) -> 0 | I11: =H11-G11 -> 0
A12: 45931 | B12: 45961 | C12: Oct 2025 | D12: =Cfg_BaselineOpeningValue + SUMIFS(Mov_Value, Mov_Date, ">"&Cfg_BaselineDate, Mov_Date, "<"&$A12) -> 0 | E12: =SUMIFS(Mov_Value, Mov_Type, "Receipt", Mov_Date, ">="&$A12, Mov_Date, "<="&$B12) -> 0 | F12: =Cfg_BaselineOpeningValue + SUMIFS(Mov_Value, Mov_Date, ">"&Cfg_BaselineDate, Mov_Date, "<="&$B12) -> 0 | G12: =D12+E12-F12 -> 0 | H12: =SUMIFS(Sales_Amount, Sales_Date, ">="&$A12, Sales_Date, "<="&$B12) -> 0 | I12: =H12-G12 -> 0
A13: 45962 | B13: 45991 | C13: Nov 2025 | D13: =Cfg_BaselineOpeningValue + SUMIFS(Mov_Value, Mov_Date, ">"&Cfg_BaselineDate, Mov_Date, "<"&$A13) -> 0 | E13: =SUMIFS(Mov_Value, Mov_Type, "Receipt", Mov_Date, ">="&$A13, Mov_Date, "<="&$B13) -> 0 | F13: =Cfg_BaselineOpeningValue + SUMIFS(Mov_Value, Mov_Date, ">"&Cfg_BaselineDate, Mov_Date, "<="&$B13) -> 0 | G13: =D13+E13-F13 -> 0 | H13: =SUMIFS(Sales_Amount, Sales_Date, ">="&$A13, Sales_Date, "<="&$B13) -> 0 | I13: =H13-G13 -> 0

Sheet Analytics
A1: MonthLabel | B1: StartDate | C1: EndDate | D1: TotalConsumption | E1: MonthlyCOGS
A2: Jun 2025 | B2: 45809 | C2: 45838 | D2: =SUMIFS(-Mov_Qty, Mov_Type, "Consumption", Mov_Date, ">="&Analytics!$B$2, Mov_Date, "<="&Analytics!$C$2) -> 0 | E2: =SUMIFS(Mov_COGSValue, Mov_Date, ">="&Analytics!$B$2, Mov_Date, "<="&Analytics!$C$2) -> 0
A3: Jul 2025 | B3: 45839 | C3: 45869 | D3: =SUMIFS(-Mov_Qty, Mov_Type, "Consumption", Mov_Date, ">="&Analytics!$B$3, Mov_Date, "<="&Analytics!$C$3) -> 0 | E3: =SUMIFS(Mov_COGSValue, Mov_Date, ">="&Analytics!$B$3, Mov_Date, "<="&Analytics!$C$3) -> 0
A4: Aug 2025 | B4: 45870 | C4: 45900 | D4: =SUMIFS(-Mov_Qty, Mov_Type, "Consumption", Mov_Date, ">="&Analytics!$B$4, Mov_Date, "<="&Analytics!$C$4) -> 0 | E4: =SUMIFS(Mov_COGSValue, Mov_Date, ">="&Analytics!$B$4, Mov_Date, "<="&Analytics!$C$4) -> 0
A5: Sep 2025 | B5: 45901 | C5: 45930 | D5: =SUMIFS(-Mov_Qty, Mov_Type, "Consumption", Mov_Date, ">="&Analytics!$B$5, Mov_Date, "<="&Analytics!$C$5) -> 0 | E5: =SUMIFS(Mov_COGSValue, Mov_Date, ">="&Analytics!$B$5, Mov_Date, "<="&Analytics!$C$5) -> 0
A6: Oct 2025 | B6: 45931 | C6: 45961 | D6: =SUMIFS(-Mov_Qty, Mov_Type, "Consumption", Mov_Date, ">="&Analytics!$B$6, Mov_Date, "<="&Analytics!$C$6) -> 0 | E6: =SUMIFS(Mov_COGSValue, Mov_Date, ">="&Analytics!$B$6, Mov_Date, "<="&Analytics!$C$6) -> 0
A7: Nov 2025 | B7: 45962 | C7: 45991 | D7: =SUMIFS(-Mov_Qty, Mov_Type, "Consumption", Mov_Date, ">="&Analytics!$B$7, Mov_Date, "<="&Analytics!$C$7) -> 0 | E7: =SUMIFS(Mov_COGSValue, Mov_Date, ">="&Analytics!$B$7, Mov_Date, "<="&Analytics!$C$7) -> 0

Sheet Dashboard
A1: Inventory Dashboard + Periodic P&L KPIs
A3: As of (Config!Today): | B3: =Cfg_Today -> 0
A5: Out of Stock (OnHand ≤ 0) | B5: =COUNTIF(Items!J2:J1004, "<=0") -> 0
A6: Need to Order (OnHand ≤ MinStock) | B6: =COUNTIF(Items!R2:R1004, "Yes") -> 0
A7: High Movers Insufficient (OnHand < ReorderPoint) | B7: =SUMPRODUCT((Items!P2:P1004="Yes")*(Items!J2:J1004<Items!Q2:Q1004)) -> 0
A9: Total Stock Value | B9: =SUM(Items!K2:K1004) -> 0
A10: COGS (This Month) | B10: =SUMIFS(Mov_COGSValue, Mov_Date, ">="&EOMONTH(Cfg_Today,-1)+1, Mov_Date, "<="&EOMONTH(Cfg_Today,0)) -> 0
A12: List: Out of Stock Items
A13: {=IFERROR(_xlfn._xlws.FILTER(Items!A2:S1004, Items!J2:J1004<=0), "None")} -> 0
A17: List: Need to Order (with Suggested Order Qty)
A18: {=IFERROR(_xlfn._xlws.FILTER(Items!A2:S1004, Items!R2:R1004="Yes"), "None")} -> 0
A22: List: High Movers with Insufficient Stock
A23: {=IFERROR(_xlfn._xlws.FILTER(Items!A2:S1004, (Items!P2:P1004="Yes")*(Items!J2:J1004<Items!Q2:Q1004)), "None")} -> 0

Sheet README
A1: HOW TO USE: 1) Config: set BaselineDate (day before your first movement) and BaselineOpeningValue (₹). Today controls month filters. 2) Items: update master (A:K). Columns after that auto-calc OnHand, StockValue, 3-month consumption, Reorder Point, Suggested Order Qty, CoverageDays. 3) Movements: record receipts (+) and consumptions (−). Value auto from Cost_No_Tax via VLOOKUP. 4) Dashboard: Out of Stock, Need to Order, High Movers insufficient, Total Stock Value, COGS (This Month) + filtered lists. 5) PnL_Daily/Weekly/Monthly: Periodic COGS (Opening + Purchases − Closing), Revenue (if Sales used), Gross Profit. 6) Analytics: 6-month trends for consumption and COGS (charts on Dashboard). Notes: FILTER requires Excel 365 or Google Sheets. For weighted average/FIFO batches, extend Movements with batch costs.
